dotserve/__init__.py
dotserve/__main__.py
dotserve/action.py
dotserve/auth.py
dotserve/cache.py
dotserve/chat_settings.py
dotserve/cli/__init__.py
dotserve/cli/utils.py
dotserve/client/acl.py
dotserve/client/base.py
dotserve/client/cloud.py
dotserve/config.py
dotserve/context.py
dotserve/element.py
dotserve/emitter.py
dotserve/frontend/dist/assets/index-207ba4b4.js
dotserve/frontend/dist/assets/index-284e06a0.js
dotserve/frontend/dist/assets/index-baf75962.css
dotserve/frontend/dist/assets/logo_dark-bc7401f6.svg
dotserve/frontend/dist/assets/logo_light-f19fc2ea.svg
dotserve/frontend/dist/favicon.svg
dotserve/frontend/dist/index.html
dotserve/haystack/__init__.py
dotserve/haystack/callbacks.py
dotserve/hello.py
dotserve/input_widget.py
dotserve/langchain/__init__.py
dotserve/langchain/callbacks.py
dotserve/langflow/__init__.py
dotserve/llama_index/__init__.py
dotserve/llama_index/callbacks.py
dotserve/logger.py
dotserve/markdown.py
dotserve/message.py
dotserve/oauth_providers.py
dotserve/playground/__init__.py
dotserve/playground/config.py
dotserve/playground/provider.py
dotserve/playground/providers/__init__.py
dotserve/playground/providers/anthropic.py
dotserve/playground/providers/huggingface.py
dotserve/playground/providers/langchain.py
dotserve/playground/providers/openai.py
dotserve/playground/providers/vertexai.py
dotserve/prompt.py
dotserve/py.typed
dotserve/secret.py
dotserve/server.py
dotserve/session.py
dotserve/socket.py
dotserve/sync.py
dotserve/telemetry.py
dotserve/types.py
dotserve/user_session.py
dotserve/utils.py
dotserve/version.py
dotserve-0.7.12.1.dist-info/METADATA
dotserve-0.7.12.1.dist-info/WHEEL
dotserve-0.7.12.1.dist-info/entry_points.txt
dotserve-0.7.12.1.dist-info/RECORD
