Metadata-Version: 2.1
Name: dotserve
Version: 0.7.12.1
Summary: A faster way to build chatbot UIs.
Home-page: https://github.com/dot-agent/dotagent
License: Apache-2.0 license
Keywords: LLM,Agents,gen ai,chat ui,chatbot ui,langchain
Author: Dotserve
Requires-Python: >=3.8.1,<4.0.0
Classifier: License :: Other/Proprietary License
Classifier: Programming Language :: Python :: 3
Classifier: Programming Language :: Python :: 3.9
Classifier: Programming Language :: Python :: 3.10
Classifier: Programming Language :: Python :: 3.11
Requires-Dist: aiofiles (>=23.1.0,<24.0.0)
Requires-Dist: aiohttp (>=3.8.4,<4.0.0)
Requires-Dist: asyncer (>=0.0.2,<0.0.3)
Requires-Dist: click (>=8.1.3,<9.0.0)
Requires-Dist: dataclasses_json (>=0.5.7,<0.6.0)
Requires-Dist: fastapi (>=0.100.0,<0.101.0)
Requires-Dist: fastapi-socketio (>=0.0.10,<0.0.11)
Requires-Dist: filetype (>=1.2.0,<2.0.0)
Requires-Dist: lazify (>=0.4.0,<0.5.0)
Requires-Dist: nest-asyncio (>=1.5.6,<2.0.0)
Requires-Dist: packaging (>=23.1,<24.0)
Requires-Dist: prisma (>=0.10.0,<0.11.0)
Requires-Dist: pydantic (>=1,<3)
Requires-Dist: pyjwt (>=2.8.0,<3.0.0)
Requires-Dist: python-dotenv (>=1.0.0,<2.0.0)
Requires-Dist: python-graphql-client (>=0.4.3,<0.5.0)
Requires-Dist: python-multipart (>=0.0.6,<0.0.7)
Requires-Dist: syncer (>=2.0.3,<3.0.0)
Requires-Dist: tomli (>=2.0.1,<3.0.0)
Requires-Dist: uptrace (>=1.18.0,<2.0.0)
Requires-Dist: uvicorn (>=0.23.2,<0.24.0)
Requires-Dist: watchfiles (>=0.20.0,<0.21.0)
Project-URL: Repository, https://github.com/dot-agent/dotagent
